{
  "tags": [
    "Tarjeta",
    "Sony",
    "store"
  ],
  "slug": "p/sony-playstation-store-us",
  "thumbnail": "https://github.com/playec/playec.github.io/blob/main/public/uploads/playstation-store.png?raw=true",
  "date": "2025-02-17T11:51:00-05:00",
  "cards": [
    {
      "value": 10,
      "price": 10.70
    },
    {
      "value": 25,
      "price": 26.75
    },
    {
      "value": 50,
      "price": 53.50
    },
    {
      "value": 75,
      "price": 80.25
    },
    {
      "value": 100,
      "price": 107.00
    }
  ],
  "title": "Sony PlayStation Store US",
  "content": "Los **códigos de recarga de PlayStation** son tarjetas digitales o físicas que contienen un código alfanumérico que permite añadir fondos a la **cartera de PlayStation Network (PSN)**. Estos fondos pueden utilizarse para:\n\n### 1. **Comprar juegos, DLCs, temas y avatares** en la PlayStation Store.\n### 2. **Renovar suscripciones** como PlayStation Plus o PlayStation Now.\n### 3. **Adquirir contenido adicional** como paquetes de expansión o microtransacciones en juegos.\n\nLos códigos de recarga están disponibles en diferentes denominaciones (por ejemplo, $10, $20, $50 USD o su equivalente en otras monedas) y pueden comprarse en tiendas físicas, en línea o a través de distribuidores autorizados. Una vez que se canjea el código, el saldo se añade a la cuenta de PSN y puede usarse en cualquier consola PlayStation (PS4, PS5) o en la tienda web de PlayStation."
}
